nrgrank/__init__.py
nrgrank/general_functions.py
nrgrank/generate_conformers.py
nrgrank/process_ligands.py
nrgrank/process_target.py
nrgrank/rank_molecules.py
nrgrank/deps/atom_type_radius.json
nrgrank/deps/matrix/MC_5p_norm_P10_M2_2.npy
nrgrank/deps/matrix/MC_5p_norm_P10_M2_2.txt
nrgrank/deps/matrix/MC_5p_norm_P10_M2_2_multiplied_2.npy
nrgrank/deps/matrix/MC_st0r5.2_6.npy
nrgrank/deps/matrix/MC_st0r5.2_6.txt
nrgrank/deps/matrix/matrix_supp.txt
nrgrank/deps/matrix/original_matrix.npy
nrgrank-1.0.13.dist-info/licenses/LICENSE
nrgrank-1.0.13.dist-info/METADATA
nrgrank-1.0.13.dist-info/WHEEL
nrgrank-1.0.13.dist-info/top_level.txt
nrgrank-1.0.13.dist-info/RECORD
