Metadata-Version: 2.4
Name: nrgrank
Version: 1.0.13
Summary: A Python based virtual screening software!
Author-email: Thomas DesCôteaux <thomas.descoteaux@umontreal.ca>, Rafael Najmanovich <rafael.najmanovich@umontreal.ca>
Maintainer-email: Thomas DesCôteaux <thomas.descoteaux@umontreal.ca>
License-Expression: GPL-3.0-or-later
Project-URL: Repository, https://github.com/NRGlab/NRGRank
Requires-Python: >=3.9
License-File: LICENSE
Requires-Dist: scipy
Requires-Dist: numpy
Requires-Dist: numba
Provides-Extra: rdkit
Requires-Dist: rdkit; extra == "rdkit"
Dynamic: license-file
